README.md
setup.py
django_sofa.egg-info/PKG-INFO
django_sofa.egg-info/SOURCES.txt
django_sofa.egg-info/dependency_links.txt
django_sofa.egg-info/not-zip-safe
django_sofa.egg-info/requires.txt
django_sofa.egg-info/top_level.txt
sofa/__init__.py
sofa/admin.py
sofa/apps.py
sofa/base.py
sofa/loader.py
sofa/managers.py
sofa/models.py
sofa/tests.py
sofa/urls.py
sofa/views.py
sofa/management/__init__.py
sofa/management/commands/__init__.py
sofa/management/commands/sofa_init_revision.py
sofa/migrations/0001_initial.py
sofa/migrations/0002_auto_20210502_2022.py
sofa/migrations/0003_replicationlog.py
sofa/migrations/0004_auto_20210901_1549.py
sofa/migrations/0005_auto_20211020_1532.py
sofa/migrations/0006_auto_20211020_1536.py
sofa/migrations/0007_auto_20211020_1538.py
sofa/migrations/__init__.py